ckxtraceviewer/__init__.py
ckxtraceviewer/ckxrender_in_ida.py
ckxtraceviewer/gui.py
ckxtraceviewer/mainlogic.py
ckxtraceviewer/test_mainui.py
ckxtraceviewer/ui/__init__.py
ckxtraceviewer/ui/ckxtraceform.py
ckxtraceviewer-1.1.dist-info/LICENSE
ckxtraceviewer-1.1.dist-info/METADATA
ckxtraceviewer-1.1.dist-info/WHEEL
ckxtraceviewer-1.1.dist-info/top_level.txt
ckxtraceviewer-1.1.dist-info/RECORD
