Metadata-Version: 2.1
Name: ckxtraceviewer
Version: 1.1
Summary: IDA plugin to embed a trace view inside IDA
Home-page: https://www.github.com/ckxckx/ckxtraceviewer
Author: Chen KX
Author-email: ckx1025ckx@gmail.com
License: BSD
Platform: UNKNOWN
Classifier: Development Status :: 5 - Production/Stable
Classifier: Environment :: Plugins
Classifier: License :: OSI Approved :: BSD License
Classifier: Programming Language :: Python :: 2.7
Classifier: Programming Language :: Python :: 3
Requires-Dist: monkeyhex (>=1.0)
